mlflow_k8sstore/__init__.py
mlflow_k8sstore/mlflow_k8sstore.py
mlflow_k8sstore_plugin-0.0.2.dist-info/METADATA
mlflow_k8sstore_plugin-0.0.2.dist-info/WHEEL
mlflow_k8sstore_plugin-0.0.2.dist-info/entry_points.txt
mlflow_k8sstore_plugin-0.0.2.dist-info/top_level.txt
mlflow_k8sstore_plugin-0.0.2.dist-info/RECORD
