Metadata-Version: 2.1
Name: mlflow-k8sstore-plugin
Version: 0.0.2
Summary: Test plugin for MLflow
Requires-Dist: mlflow ==2.6.0
